odoo/addons/helpdesk_autoclose/.python-version
odoo/addons/helpdesk_autoclose/README.md
odoo/addons/helpdesk_autoclose/__init__.py
odoo/addons/helpdesk_autoclose/__manifest__.py
odoo/addons/helpdesk_autoclose/data/helpdesk_autoclose_cron.xml
odoo/addons/helpdesk_autoclose/models/__init__.py
odoo/addons/helpdesk_autoclose/models/helpdesk_stage.py
odoo/addons/helpdesk_autoclose/views/helpdesk_ticket_stage_autoclose.xml
odoo12_addon_helpdesk_autoclose-12.0.0.1.0.99.dev4.dist-info/METADATA
odoo12_addon_helpdesk_autoclose-12.0.0.1.0.99.dev4.dist-info/WHEEL
odoo12_addon_helpdesk_autoclose-12.0.0.1.0.99.dev4.dist-info/top_level.txt
odoo12_addon_helpdesk_autoclose-12.0.0.1.0.99.dev4.dist-info/RECORD
