Metadata-Version: 2.1
Name: odoo12-addon-helpdesk-autoclose
Version: 12.0.0.1.0.99.dev4
Summary: ODOO helpdesk customizations for social cooperatives. Handle mails through ODOO and link them to knowledge.
Home-page: https://gitlab.com/somitcoop/erp-research/odoo-helpdesk
Author: Som It Cooperatiu SCCL
License: AGPL-3
Platform: UNKNOWN
Classifier: Programming Language :: Python
Classifier: Framework :: Odoo
Classifier: Framework :: Odoo :: 12.0
Classifier: License :: OSI Approved :: GNU Affero General Public License v3
Requires-Python: >=3.5
Requires-Dist: odoo12-addon-helpdesk-mgmt
Requires-Dist: odoo <12.1dev,>=12.0a
